{
  "phase": "ENGINE_PHASE_4",
  "gate": "GATE_C",
  "task": "independent-gold-adjudication-preparation",
  "source_fixture_version": "engine-phase-4-representative-public-gold/v1",
  "candidate_gold_policy_version": "engine-phase-4-representative-gold-policy/v1",
  "case_count": 24,
  "case_ids": [
    "p4c_001_student_affairs_special",
    "p4c_002_national_second_round",
    "p4c_003_hope_ladder_extension",
    "p4c_004_national_work_result",
    "p4c_005_miraero_second",
    "p4c_006_gwangsan_extension",
    "p4c_007_sejong_internal_guidance",
    "p4c_008_cau_welfare_result_2025_1",
    "p4c_009_cau_welfare_result_2024_2",
    "p4c_010_cau_national_preapplication",
    "p4c_011_cau_innovation_hwp",
    "p4c_012_history_central_love",
    "p4c_013_history_growth_table",
    "p4c_014_youth_farmer_image",
    "p4c_015_seoul_talent_hwp",
    "p4c_016_asan_hope_hwpx",
    "p4c_017_uic_2025_fall",
    "p4c_018_uic_samsung_updated",
    "p4c_019_uic_legacy",
    "p4c_020_uic_supporters_table",
    "p4c_021_grad_need_based",
    "p4c_022_grad_seoul_foundation_pdf",
    "p4c_023_russian_alumni_funds",
    "p4c_024_dean_recommendation_guidance"
  ],
  "source_case_manifest_hash": "51567d8e11508992ea0f2a9bef4473415f2f05a8587268da6f9b9a0520725471",
  "corpus_freeze_sha": "f410929e93f7f003ad39a03a2376b4a24ef755dc",
  "relation_correction_sha": "3f5d26cd0128083b240f9ae5d8a7fa513ee63a3c",
  "adjudication_schema_version": "engine-phase-4-gate-c-adjudication/v1",
  "adjudication_status": "pending_independent_review",
  "independent_reviewer_required": true,
  "created_at": "2026-07-19T12:00:00Z",
  "reviewed_case_count": 0,
  "approved_case_count": 0,
  "corrected_case_count": 0,
  "unresolved_case_count": 0
}
